AUTHORS.rst
CONTRIBUTING.rst
HISTORY.rst
LICENSE
MANIFEST.in
README.rst
setup.cfg
setup.py
docs/Makefile
docs/authors.rst
docs/conf.py
docs/contributing.rst
docs/history.rst
docs/index.rst
docs/installation.rst
docs/make.bat
docs/readme.rst
docs/usage.rst
indaba/__init__.py
indaba/settings.py
indaba/urls.py
indaba/wsgi.py
indaba.egg-info/PKG-INFO
indaba.egg-info/SOURCES.txt
indaba.egg-info/dependency_links.txt
indaba.egg-info/entry_points.txt
indaba.egg-info/not-zip-safe
indaba.egg-info/requires.txt
indaba.egg-info/top_level.txt
indaba/accounts/__init__.py
indaba/accounts/admin.py
indaba/accounts/apps.py
indaba/accounts/forms.py
indaba/accounts/models.py
indaba/accounts/tests.py
indaba/accounts/urls.py
indaba/accounts/views.py
indaba/accounts/migrations/0001_initial.py
indaba/accounts/migrations/__init__.py
indaba/accounts/templates/accounts/login.html
indaba/accounts/templates/accounts/signup.html
indaba/core/__init__.py
indaba/core/admin.py
indaba/core/apps.py
indaba/core/models.py
indaba/core/tests.py
indaba/core/views.py
indaba/core/migrations/0001_initial.py
indaba/core/migrations/__init__.py
indaba/profiles/__init__.py
indaba/profiles/admin.py
indaba/profiles/apps.py
indaba/profiles/models.py
indaba/profiles/tests.py
indaba/profiles/views.py
indaba/profiles/migrations/0001_initial.py
indaba/profiles/migrations/__init__.py
indaba/static/css/bootstrap-responsive.css
indaba/static/css/bootstrap.css
indaba/static/css/fontello-ie7.css
indaba/static/css/fontello.css
indaba/static/css/prettyPhoto.css
indaba/static/css/style.css
indaba/static/font/fontello.eot
indaba/static/font/fontello.svg
indaba/static/font/fontello.ttf
indaba/static/font/fontello.woff
indaba/static/img/blog_img-01.jpg
indaba/static/img/blog_img-02.jpg
indaba/static/img/blog_img-03.jpg
indaba/static/img/favicon.ico
indaba/static/img/glyphicons-halflings.png
indaba/static/img/grey-cardboard-bg.png
indaba/static/img/logo.png
indaba/static/img/portfolio-01.jpg
indaba/static/img/portfolio-02.jpg
indaba/static/img/portfolio-03.jpg
indaba/static/img/portrait-1.jpg
indaba/static/img/portrait-2.jpg
indaba/static/img/portrait-3.jpg
indaba/static/img/portrait-4.jpg
indaba/static/img/top-bgs.jpg
