Metadata-Version: 1.1
Name: indaba
Version: 0.1.2
Summary: simple conference management system
Home-page: https://gitlab.com/hbutau/indaba
Author: Humphrey Butau
Author-email: hbutau35@gmail.com
License: MIT license
Keywords: indaba
Platform: UNKNOWN
Classifier: Development Status :: 2 - Pre-Alpha
Classifier: Intended Audience :: Developers
Classifier: License :: OSI Approved :: MIT License
Classifier: Natural Language :: English
Classifier: Programming Language :: Python :: 2
Classifier: Programming Language :: Python :: 2.6
Classifier: Programming Language :: Python :: 2.7
Classifier: Programming Language :: Python :: 3
Classifier: Programming Language :: Python :: 3.3
Classifier: Programming Language :: Python :: 3.4
Classifier: Programming Language :: Python :: 3.5
